{"assets":[],"layers":[{"ddd":0,"ind":1,"ty":4,"nm":"形状图层 3","ks":{"o":{"k":30},"r":{"k":[{"i":{"x":[0.833],"y":[0.833]},"o":{"x":[0.167],"y":[0.167]},"n":["0p833_0p833_0p167_0p167"],"t":1,"s":[-23],"e":[0]},{"t":25}]},"p":{"k":[320,375,0]},"a":{"k":[-41,-81,0]},"s":{"k":[100,100,100]}},"ao":0,"shapes":[{"ty":"gr","it":[{"d":1,"ty":"el","s":{"k":[11,11]},"p":{"k":[0,0]},"nm":"椭圆路径 1","mn":"ADBE Vector Shape - Ellipse"},{"ty":"fl","fillEnabled":true,"c":{"k":[0.08,0.18,0.31,1]},"o":{"k":100},"nm":"填充 1","mn":"ADBE Vector Graphic - Fill"},{"ty":"tr","p":{"k":[82,-373],"ix":2},"a":{"k":[0,0],"ix":1},"s":{"k":[100,100],"ix":3},"r":{"k":0,"ix":6},"o":{"k":100,"ix":7},"sk":{"k":0,"ix":4},"sa":{"k":0,"ix":5},"nm":"变换"}],"nm":"椭圆 1","np":3,"mn":"ADBE Vector Group"}],"ip":0,"op":200,"st":0,"bm":0,"sr":1},{"ddd":0,"ind":2,"ty":4,"nm":"形状图层 4","ks":{"o":{"k":30},"r":{"k":0},"p":{"k":[{"i":{"x":0.833,"y":0.833},"o":{"x":0.167,"y":0.167},"n":"0p833_0p833_0p167_0p167","t":1,"s":[132.471,100.375,0],"e":[220.125,94.375,0],"to":[60.3210296630859,0,0],"ti":[-2.7548463344574,0,0]},{"t":25}]},"a":{"k":[-163,-274,0]},"s":{"k":[{"i":{"x":[0.833,0.833,0.833],"y":[0.833,0.833,0.833]},"o":{"x":[0.167,0.167,0.167],"y":[0.167,0.167,0.167]},"n":["0p833_0p833_0p167_0p167","0p833_0p833_0p167_0p167","0p833_0p833_0p167_0p167"],"t":1,"s":[11.408,11.408,100],"e":[100,100,100]},{"t":25}]}},"ao":0,"shapes":[{"ty":"gr","it":[{"ind":0,"ty":"sh","ks":{"k":{"i":[[12.125,2.375],[0,0],[0,0],[0,0],[-3.25,5.125],[0,0]],"o":[[11.125,4],[0,0],[0,0],[0,0],[1.152,-1.816],[0,0]],"v":[[-156.125,-260.125],[-145.625,-250.625],[-142,-248.25],[-140,-250.625],[-137.875,-258.25],[-142.75,-252.25]],"c":true}},"nm":"路径 1","mn":"ADBE Vector Shape - Group"},{"ty":"fl","fillEnabled":true,"c":{"k":[0.08,0.18,0.31,1]},"o":{"k":100},"nm":"填充 1","mn":"ADBE Vector Graphic - Fill"},{"ty":"tr","p":{"k":[0,0],"ix":2},"a":{"k":[0,0],"ix":1},"s":{"k":[100,100],"ix":3},"r":{"k":0,"ix":6},"o":{"k":100,"ix":7},"sk":{"k":0,"ix":4},"sa":{"k":0,"ix":5},"nm":"变换"}],"nm":"形状 4","np":3,"mn":"ADBE Vector Group"},{"ty":"gr","it":[{"ind":0,"ty":"sh","ks":{"k":{"i":[[7.625,-1],[-0.25,0.25],[0.125,-0.25],[-0.25,-0.25],[-5.5,8.75],[0.125,-0.25]],"o":[[22.25,5.125],[3,0.5],[0,-0.875],[-1.25,-2.375],[-6.25,1.5],[-3,-9]],"v":[[-167,-314],[-147.375,-296.5],[-140.75,-294],[-136.5,-296.625],[-132.25,-311.125],[-141.5,-301.5]],"c":true}},"nm":"路径 1","mn":"ADBE Vector Shape - Group"},{"ty":"fl","fillEnabled":true,"c":{"k":[0.08,0.18,0.31,1]},"o":{"k":100},"nm":"填充 1","mn":"ADBE Vector Graphic - Fill"},{"ty":"tr","p":{"k":[-38.375,29.75],"ix":2},"a":{"k":[0,0],"ix":1},"s":{"k":[100,100],"ix":3},"r":{"k":0,"ix":6},"o":{"k":100,"ix":7},"sk":{"k":0,"ix":4},"sa":{"k":0,"ix":5},"nm":"变换"}],"nm":"形状 3","np":3,"mn":"ADBE Vector Group"},{"ty":"gr","it":[{"ind":0,"ty":"sh","ks":{"k":{"i":[[7.625,-1],[-0.438,-1.563],[0,0],[-0.25,-0.25],[0,0],[1,-5.5]],"o":[[15.75,6.5],[2.688,-1.313],[0,0],[-2.125,-2.375],[0,0],[-2.25,-4.25]],"v":[[-177.125,-298.625],[-167.375,-284.375],[-160.375,-283.125],[-155.25,-286.5],[-152,-300.625],[-160.25,-289.75]],"c":true}},"nm":"路径 1","mn":"ADBE Vector Shape - Group"},{"ty":"fl","fillEnabled":true,"c":{"k":[0.08,0.18,0.31,1]},"o":{"k":100},"nm":"填充 1","mn":"ADBE Vector Graphic - Fill"},{"ty":"tr","p":{"k":[0,0],"ix":2},"a":{"k":[0,0],"ix":1},"s":{"k":[100,100],"ix":3},"r":{"k":0,"ix":6},"o":{"k":100,"ix":7},"sk":{"k":0,"ix":4},"sa":{"k":0,"ix":5},"nm":"变换"}],"nm":"形状 2","np":3,"mn":"ADBE Vector Group"}],"ip":0,"op":200,"st":0,"bm":0,"sr":1},{"ddd":0,"ind":3,"ty":4,"nm":"boat","ks":{"o":{"k":30},"r":{"k":0},"p":{"k":[{"i":{"x":0.833,"y":0.833},"o":{"x":0.167,"y":0.167},"n":"0p833_0p833_0p167_0p167","t":1,"s":[190,406,0],"e":[320,406,0],"to":[18.974573135376,0.29191651940346,0],"ti":[-2.69209313392639,-0.0414168164134,0]},{"t":25}]},"a":{"k":[0,0,0]},"s":{"k":[100,100,100]}},"ao":0,"shapes":[{"ty":"gr","it":[{"ind":0,"ty":"sh","ks":{"k":{"i":[[-4,6.125],[0,0],[0,0],[0,0]],"o":[[-44.875,20.25],[0,0],[0,0],[0,0]],"v":[[-141.125,-232.75],[-209.375,-220.375],[-203.75,-204.375],[-159,-204.5]],"c":true}},"nm":"路径 1","mn":"ADBE Vector Shape - Group"},{"ty":"fl","fillEnabled":true,"c":{"k":[0.08,0.18,0.31,1]},"o":{"k":100},"nm":"填充 1","mn":"ADBE Vector Graphic - Fill"},{"ty":"tr","p":{"k":[231,-1],"ix":2},"a":{"k":[0,0],"ix":1},"s":{"k":[100,100],"ix":3},"r":{"k":0,"ix":6},"o":{"k":100,"ix":7},"sk":{"k":0,"ix":4},"sa":{"k":0,"ix":5},"nm":"变换"}],"nm":"形状 4","np":3,"mn":"ADBE Vector Group"}],"ip":0,"op":200,"st":0,"bm":0,"sr":1},{"ddd":0,"ind":4,"ty":4,"nm":"形状图层 2","ks":{"o":{"k":20},"r":{"k":0},"p":{"k":[320,413,0]},"a":{"k":[0,0,0]},"s":{"k":[100,100,100]}},"ao":0,"shapes":[{"ty":"gr","it":[{"ind":0,"ty":"sh","ks":{"k":{"i":[[33,-0.5],[0,0],[0,0],[-39.5,1.5]],"o":[[-33.5,0.5],[0,0],[0,0],[-59.5,-8.5]],"v":[[-277,-316],[-324.5,-275],[-324.5,-204.5],[-134,-205.5]],"c":true}},"nm":"路径 1","mn":"ADBE Vector Shape - Group"},{"ty":"fl","fillEnabled":true,"c":{"k":[0.08,0.18,0.31,1]},"o":{"k":100},"nm":"填充 1","mn":"ADBE Vector Graphic - Fill"},{"ty":"tr","p":{"k":[0,0],"ix":2},"a":{"k":[0,0],"ix":1},"s":{"k":[100,100],"ix":3},"r":{"k":0,"ix":6},"o":{"k":100,"ix":7},"sk":{"k":0,"ix":4},"sa":{"k":0,"ix":5},"nm":"变换"}],"nm":"形状 1","np":3,"mn":"ADBE Vector Group"},{"ty":"gr","it":[{"ind":0,"ty":"sh","ks":{"k":{"i":[[0,0],[0,0],[0,0],[0,0]],"o":[[-137,79],[0,0],[0,0],[0,0]],"v":[[-169,-291],[-413.5,-206],[-118,-206],[-118.5,-291]],"c":true}},"nm":"路径 1","mn":"ADBE Vector Shape - Group"},{"ty":"fl","fillEnabled":true,"c":{"k":[0.08,0.18,0.31,1]},"o":{"k":100},"nm":"填充 1","mn":"ADBE Vector Graphic - Fill"},{"ty":"tr","p":{"k":[490,0],"ix":2},"a":{"k":[0,0],"ix":1},"s":{"k":[100,100],"ix":3},"r":{"k":0,"ix":6},"o":{"k":100,"ix":7},"sk":{"k":0,"ix":4},"sa":{"k":0,"ix":5},"nm":"变换"}],"nm":"形状 3","np":3,"mn":"ADBE Vector Group"}],"ip":0,"op":200,"st":0,"bm":0,"sr":1},{"ddd":0,"ind":5,"ty":4,"nm":"形状图层 1","ks":{"o":{"k":20},"r":{"k":0},"p":{"k":[320,413,0]},"a":{"k":[0,0,0]},"s":{"k":[100,100,100]}},"ao":0,"shapes":[{"ty":"gr","it":[{"ind":0,"ty":"sh","ks":{"k":{"i":[[56.5,1],[0,0],[0,0],[-72.5,0]],"o":[[-33.5,0.5],[0,0],[0,0],[-132.5,-18.5]],"v":[[-277,-316],[-324.5,-275],[-325,-133],[-23.5,-135]],"c":true}},"nm":"路径 1","mn":"ADBE Vector Shape - Group"},{"ty":"fl","fillEnabled":true,"c":{"k":[0.08,0.18,0.31,1]},"o":{"k":100},"nm":"填充 1","mn":"ADBE Vector Graphic - Fill"},{"ty":"tr","p":{"k":[-26,-70],"ix":2},"a":{"k":[0,0],"ix":1},"s":{"k":[100,100],"ix":3},"r":{"k":0,"ix":6},"o":{"k":100,"ix":7},"sk":{"k":0,"ix":4},"sa":{"k":0,"ix":5},"nm":"变换"}],"nm":"形状 2","np":3,"mn":"ADBE Vector Group"},{"ty":"gr","it":[{"ind":0,"ty":"sh","ks":{"k":{"i":[[0,0],[36.648,-8.762],[61.752,-13.693],[0,0]],"o":[[0,0],[-55.588,13.29],[-0.008,-0.301],[0,0]],"v":[[361.833,-137.797],[268.64,-169.27],[106.96,-105.651],[361.763,-106.076]],"c":true}},"nm":"路径 1","mn":"ADBE Vector Shape - Group"},{"ty":"fl","fillEnabled":true,"c":{"k":[0.08,0.18,0.31,1]},"o":{"k":100},"nm":"填充 1","mn":"ADBE Vector Graphic - Fill"},{"ty":"tr","p":{"k":[-26,-70],"ix":2},"a":{"k":[0,0],"ix":1},"s":{"k":[98.556,128.246],"ix":3},"r":{"k":0,"ix":6},"o":{"k":100,"ix":7},"sk":{"k":0,"ix":4},"sa":{"k":0,"ix":5},"nm":"变换"}],"nm":"形状 4","np":3,"mn":"ADBE Vector Group"}],"ip":0,"op":200,"st":0,"bm":0,"sr":1}],"v":"4.5.3","ddd":0,"ip":0,"op":50,"fr":25,"w":640,"h":200}